{
  "kind": "Requirement",
  "id": "R-crystallize-before-split",
  "claim": "On overload, an operator shall crystallize first, re-measure, and delegate (split) only if still over budget.",
  "owner": "ai-agent",
  "status": "SETTLED",
  "why": "SETTLED (P7): the order discipline is structurally bound. The apply-proposal mechanism (internal/proposal) crystallizes via Proposal types; the constitution (internal/generator/constitution.go, docs/gen/CONSTITUTION.md) names the ORDER explicitly. Splitting is for irreducible size, crystallizing is for un-offloaded knowledge; delegation is the lever of last resort. Splitting before crystallizing fragments knowledge that could have been freed in place. The over-budget REFLECTION finding (ReflectOverBudgetOperators, internal/diagnose/finding.go) renders the ordered imperative: 'crystallize first (R-crystallize-before-split); if still over, delegate a sub-domain (R-context-bounded-delegation).' The closure tool that would verify advancement before any split is considered is Planned (internal/methodology/tools_data.go).",
  "last_reviewed_at": "2026-07-13"
}
